{
  "received_ce": "SENSEX2670979000CE",
  "received_pe": "SENSEX2670979000PE",
  "scrip_master_len": 156486,
  "unique_expiries_2026": {
    "24SEP2026": [
      "SENSEX26SEP87000PE",
      "SENSEX26SEP87000CE",
      "SENSEX26SEP68000CE",
      "SENSEX26SEP85000CE",
      "SENSEX26SEP84000CE"
    ],
    "30JUL2026": [
      "SENSEX26JUL81000PE",
      "SENSEX26JUL70300CE",
      "SENSEX26JUL74300PE",
      "SENSEX26JUL72900PE",
      "SENSEX26JUL71200PE"
    ],
    "09JUL2026": [
      "SENSEX2670979200CE",
      "SENSEX2670971200PE",
      "SENSEX2670975800PE",
      "SENSEX2670978800CE",
      "SENSEX2670972800CE"
    ],
    "16JUL2026": [
      "SENSEX2671670700PE",
      "SENSEX2671682100PE",
      "SENSEX2671680700PE",
      "SENSEX2671672900CE",
      "SENSEX2671676000PE"
    ],
    "27AUG2026": [
      "SENSEX26AUG80700CE",
      "SENSEX26AUG78400PE",
      "SENSEX26AUG81100CE",
      "SENSEX26AUG70100PE",
      "SENSEX26AUG82400PE"
    ],
    "23JUL2026": [
      "SENSEX2672379300CE",
      "SENSEX2672368900CE",
      "SENSEX2672371400CE",
      "SENSEX2672372800CE",
      "SENSEX2672368900PE"
    ],
    "06AUG2026": [
      "SENSEX2680683600CE",
      "SENSEX2680675300PE",
      "SENSEX2680674600CE",
      "SENSEX2680670900CE",
      "SENSEX2680676500PE"
    ],
    "31DEC2026": [
      "SENSEX26DEC79000CE",
      "SENSEX26DEC81000CE",
      "SENSEX26DEC81000PE",
      "SENSEX26DEC78000CE",
      "SENSEX26DEC71000PE"
    ],
    "13AUG2026": [
      "SENSEX2681374100PE",
      "SENSEX2681376400PE",
      "SENSEX2681375700CE",
      "SENSEX2681370300CE",
      "SENSEX2681375900CE"
    ],
    "20AUG2026": [
      "SENSEX2682077000CE",
      "SENSEX2682079300CE",
      "SENSEX2682077900CE",
      "SENSEX2682083300CE",
      "SENSEX2682077200CE"
    ]
  }
}